geolinks/__init__.py
geolinks-0.2.3.dist-info/LICENSE.md
geolinks-0.2.3.dist-info/METADATA
geolinks-0.2.3.dist-info/WHEEL
geolinks-0.2.3.dist-info/entry_points.txt
geolinks-0.2.3.dist-info/top_level.txt
geolinks-0.2.3.dist-info/RECORD
