Metadata-Version: 2.1
Name: geolinks
Version: 0.2.3
Summary: Utilities to deal with geospatial links
Home-page: https://github.com/geopython/geolinks
Author: Tom Kralidis
Author-email: tomkralidis@gmail.com
Maintainer: Tom Kralidis
Maintainer-email: tomkralidis@gmail.com
License: MIT
Keywords: links geo protocol url href
Platform: all
Classifier: Development Status :: 4 - Beta
Classifier: Environment :: Console
Classifier: Intended Audience :: Developers
Classifier: Intended Audience :: Science/Research
Classifier: License :: OSI Approved :: MIT License
Classifier: Operating System :: OS Independent
Classifier: Programming Language :: Python
Classifier: Programming Language :: Python :: 3.5
Classifier: Topic :: Scientific/Engineering :: GIS
